{
  "$schema": "http://json-schema.org/draft-04/schema#",
  "type": "object",
  "title": "Данные криптопрофиля пользователя",
  "properties": {
    "name": {
      "type": "string",
      "title": "Наименование криптопрофиля",
      "maxLength": 255
    },
    "type": {
      "type": "string",
      "title": "Тип криптопрофиля",
      "maxLength": 255
    },
    "signChannel": {
      "type": "string",
      "title": "Канал подписи",
      "maxLength": 255
    },
    "titleName": {
      "type": "string",
      "title": "Тип подписи",
      "maxLength": 2000
    }
  }
}
